{
"nodes": [
{"name": "0"},
{"name": "1"},
{"name": "2"},
{"name": "3"},
{"name": "4"},
{"name": "5"},
{"name": "6"},
{"name": "7"},
{"name": "8"},
{"name": "9"},
{"name": "10"},
{"name": "11"},
{"name": "12"},
{"name": "13"},
{"name": "14"},
{"name": "15"},
{"name": "16"},
{"name": "17"},
{"name": "18"},
{"name": "19"},
{"name": "20"},
{"name": "21"},
{"name": "22"},
{"name": "23"},
{"name": "24"},
{"name": "25"},
{"name": "26"},
{"name": "27"},
{"name": "28"},
{"name": "29"},
{"name": "30"},
{"name": "31"},
{"name": "32"},
{"name": "33"},
{"name": "34"},
{"name": "35"},
{"name": "36"},
{"name": "37"},
{"name": "38"},
{"name": "39"},
{"name": "40"},
{"name": "41"},
{"name": "42"},
{"name": "43"},
{"name": "44"},
{"name": "45"},
{"name": "46"},
{"name": "47"},
{"name": "48"},
{"name": "49"},
{"name": "50"},
{"name": "51"},
{"name": "52"},
{"name": "53"},
{"name": "54"},
{"name": "55"},
{"name": "56"},
{"name": "57"},
{"name": "58"},
{"name": "59"},
{"name": "60"},
{"name": "61"},
{"name": "62"},
{"name": "63"},
{"name": "64"},
{"name": "65"},
{"name": "66"},
{"name": "67"},
{"name": "68"},
{"name": "69"},
{"name": "70"},
{"name": "71"},
{"name": "72"},
{"name": "73"},
{"name": "74"},
{"name": "75"},
{"name": "76"},
{"name": "77"},
{"name": "78"},
{"name": "79"},
{"name": "80"},
{"name": "81"},
{"name": "82"},
{"name": "83"},
{"name": "84"},
{"name": "85"},
{"name": "86"},
{"name": "87"},
{"name": "88"},
{"name": "89"},
{"name": "90"},
{"name": "91"},
{"name": "92"},
{"name": "93"},
{"name": "94"},
{"name": "95"},
{"name": "96"},
{"name": "97"},
{"name": "98"},
{"name": "99"},
{"name": "100"},
{"name": "101"},
{"name": "102"},
{"name": "103"},
{"name": "104"},
{"name": "105"},
{"name": "106"},
{"name": "107"},
{"name": "108"},
{"name": "109"},
{"name": "110"},
{"name": "111"},
{"name": "112"},
{"name": "113"},
{"name": "114"},
{"name": "115"},
{"name": "116"},
{"name": "117"},
{"name": "118"},
{"name": "119"},
{"name": "120"},
{"name": "121"},
{"name": "122"},
{"name": "123"},
{"name": "124"},
{"name": "125"},
{"name": "126"},
{"name": "127"},
{"name": "128"},
{"name": "129"},
{"name": "130"},
{"name": "131"},
{"name": "132"},
{"name": "133"},
{"name": "134"},
{"name": "135"},
{"name": "136"},
{"name": "137"},
{"name": "138"},
{"name": "139"},
{"name": "140"},
{"name": "141"},
{"name": "142"},
{"name": "143"},
{"name": "144"},
{"name": "145"},
{"name": "146"},
{"name": "147"},
{"name": "148"},
{"name": "149"},
{"name": "150"},
{"name": "151"},
{"name": "152"},
{"name": "153"},
{"name": "154"},
{"name": "155"},
{"name": "156"},
{"name": "157"},
{"name": "158"},
{"name": "159"},
{"name": "160"},
{"name": "161"},
{"name": "162"},
{"name": "163"},
{"name": "164"},
{"name": "165"},
{"name": "166"},
{"name": "167"},
{"name": "168"},
{"name": "169"},
{"name": "170"},
{"name": "171"},
{"name": "172"},
{"name": "173"},
{"name": "174"},
{"name": "175"},
{"name": "176"},
{"name": "177"},
{"name": "178"},
{"name": "179"},
{"name": "180"},
{"name": "181"},
{"name": "182"},
{"name": "183"},
{"name": "184"},
{"name": "185"},
{"name": "186"},
{"name": "187"},
{"name": "188"},
{"name": "189"},
{"name": "190"},
{"name": "191"},
{"name": "192"},
{"name": "193"},
{"name": "194"},
{"name": "195"},
{"name": "196"},
{"name": "197"},
{"name": "198"},
{"name": "199"},
{"name": "200"},
{"name": "201"},
{"name": "202"},
{"name": "203"},
{"name": "204"},
{"name": "205"},
{"name": "206"},
{"name": "207"},
{"name": "208"},
{"name": "209"},
{"name": "210"},
{"name": "211"},
{"name": "212"},
{"name": "213"},
{"name": "214"},
{"name": "215"},
{"name": "216"},
{"name": "217"},
{"name": "218"},
{"name": "219"},
{"name": "220"},
{"name": "221"},
{"name": "222"},
{"name": "223"},
{"name": "224"},
{"name": "225"},
{"name": "226"},
{"name": "227"},
{"name": "228"},
{"name": "229"},
{"name": "230"},
{"name": "231"},
{"name": "232"},
{"name": "233"},
{"name": "234"},
{"name": "235"},
{"name": "236"},
{"name": "237"},
{"name": "238"},
{"name": "239"},
{"name": "240"},
{"name": "241"},
{"name": "242"},
{"name": "243"},
{"name": "244"},
{"name": "245"},
{"name": "246"},
{"name": "247"},
{"name": "248"},
{"name": "249"},
{"name": "250"},
{"name": "251"},
{"name": "252"},
{"name": "253"},
{"name": "254"},
{"name": "255"},
{"name": "256"},
{"name": "257"},
{"name": "258"},
{"name": "259"},
{"name": "260"},
{"name": "261"},
{"name": "262"},
{"name": "263"},
{"name": "264"},
{"name": "265"},
{"name": "266"},
{"name": "267"},
{"name": "268"},
{"name": "269"},
{"name": "270"},
{"name": "271"},
{"name": "272"},
{"name": "273"},
{"name": "274"},
{"name": "275"},
{"name": "276"},
{"name": "277"},
{"name": "278"},
{"name": "279"},
{"name": "280"},
{"name": "281"},
{"name": "282"},
{"name": "283"},
{"name": "284"},
{"name": "285"},
{"name": "286"},
{"name": "287"},
{"name": "288"},
{"name": "289"},
{"name": "290"},
{"name": "291"},
{"name": "292"},
{"name": "293"},
{"name": "294"},
{"name": "295"},
{"name": "296"},
{"name": "297"},
{"name": "298"},
{"name": "299"},
{"name": "300"},
{"name": "301"},
{"name": "302"},
{"name": "303"},
{"name": "304"},
{"name": "305"},
{"name": "306"},
{"name": "307"},
{"name": "308"},
{"name": "309"},
{"name": "310"},
{"name": "311"},
{"name": "312"},
{"name": "313"},
{"name": "314"},
{"name": "315"},
{"name": "316"},
{"name": "317"},
{"name": "318"},
{"name": "319"},
{"name": "320"},
{"name": "321"},
{"name": "322"},
{"name": "323"},
{"name": "324"},
{"name": "325"},
{"name": "326"},
{"name": "327"},
{"name": "328"},
{"name": "329"},
{"name": "330"},
{"name": "331"},
{"name": "332"},
{"name": "333"},
{"name": "334"},
{"name": "335"},
{"name": "336"},
{"name": "337"},
{"name": "338"},
{"name": "339"},
{"name": "340"},
{"name": "341"},
{"name": "342"},
{"name": "343"},
{"name": "344"},
{"name": "345"},
{"name": "346"},
{"name": "347"},
{"name": "348"},
{"name": "349"},
{"name": "350"},
{"name": "351"},
{"name": "352"},
{"name": "353"},
{"name": "354"},
{"name": "355"},
{"name": "356"},
{"name": "357"},
{"name": "358"},
{"name": "359"},
{"name": "360"},
{"name": "361"},
{"name": "362"},
{"name": "363"},
{"name": "364"},
{"name": "365"},
{"name": "366"},
{"name": "367"},
{"name": "368"},
{"name": "369"},
{"name": "370"},
{"name": "371"},
{"name": "372"},
{"name": "373"},
{"name": "374"},
{"name": "375"},
{"name": "376"},
{"name": "377"},
{"name": "378"},
{"name": "379"},
{"name": "380"},
{"name": "381"},
{"name": "382"},
{"name": "383"},
{"name": "384"},
{"name": "385"},
{"name": "386"},
{"name": "387"},
{"name": "388"},
{"name": "389"},
{"name": "390"},
{"name": "391"},
{"name": "392"},
{"name": "393"},
{"name": "394"},
{"name": "395"},
{"name": "396"},
{"name": "397"},
{"name": "398"},
{"name": "399"},
{"name": "400"},
{"name": "401"},
{"name": "402"},
{"name": "403"},
{"name": "404"},
{"name": "405"},
{"name": "406"},
{"name": "407"},
{"name": "408"},
{"name": "409"},
{"name": "410"},
{"name": "411"},
{"name": "412"},
{"name": "413"},
{"name": "414"},
{"name": "415"},
{"name": "416"},
{"name": "417"},
{"name": "418"},
{"name": "419"},
{"name": "420"},
{"name": "421"},
{"name": "422"},
{"name": "423"},
{"name": "424"},
{"name": "425"},
{"name": "426"},
{"name": "427"},
{"name": "428"},
{"name": "429"},
{"name": "430"},
{"name": "431"},
{"name": "432"},
{"name": "433"},
{"name": "434"},
{"name": "435"},
{"name": "436"},
{"name": "437"},
{"name": "438"},
{"name": "439"},
{"name": "440"},
{"name": "441"},
{"name": "442"},
{"name": "443"},
{"name": "444"},
{"name": "445"},
{"name": "446"},
{"name": "447"},
{"name": "448"},
{"name": "449"},
{"name": "450"},
{"name": "451"},
{"name": "452"},
{"name": "453"},
{"name": "454"},
{"name": "455"},
{"name": "456"},
{"name": "457"},
{"name": "458"},
{"name": "459"},
{"name": "460"},
{"name": "461"},
{"name": "462"},
{"name": "463"},
{"name": "464"},
{"name": "465"},
{"name": "466"},
{"name": "467"},
{"name": "468"},
{"name": "469"},
{"name": "470"},
{"name": "471"},
{"name": "472"},
{"name": "473"},
{"name": "474"},
{"name": "475"},
{"name": "476"},
{"name": "477"},
{"name": "478"},
{"name": "479"},
{"name": "480"},
{"name": "481"},
{"name": "482"},
{"name": "483"},
{"name": "484"},
{"name": "485"},
{"name": "486"},
{"name": "487"},
{"name": "488"},
{"name": "489"},
{"name": "490"},
{"name": "491"},
{"name": "492"},
{"name": "493"},
{"name": "494"},
{"name": "495"},
{"name": "496"},
{"name": "497"},
{"name": "498"},
{"name": "499"},
{"name": "500"},
{"name": "501"},
{"name": "502"},
{"name": "503"},
{"name": "504"},
{"name": "505"},
{"name": "506"},
{"name": "507"},
{"name": "508"},
{"name": "509"},
{"name": "510"},
{"name": "511"},
{"name": "512"},
{"name": "513"},
{"name": "514"},
{"name": "515"},
{"name": "516"},
{"name": "517"},
{"name": "518"},
{"name": "519"},
{"name": "520"},
{"name": "521"},
{"name": "522"},
{"name": "523"},
{"name": "524"},
{"name": "525"},
{"name": "526"},
{"name": "527"},
{"name": "528"},
{"name": "529"},
{"name": "530"},
{"name": "531"},
{"name": "532"},
{"name": "533"},
{"name": "534"},
{"name": "535"},
{"name": "536"},
{"name": "537"},
{"name": "538"},
{"name": "539"},
{"name": "540"},
{"name": "541"},
{"name": "542"},
{"name": "543"},
{"name": "544"},
{"name": "545"},
{"name": "546"},
{"name": "547"},
{"name": "548"},
{"name": "549"},
{"name": "550"},
{"name": "551"},
{"name": "552"},
{"name": "553"},
{"name": "554"},
{"name": "555"},
{"name": "556"},
{"name": "557"},
{"name": "558"},
{"name": "559"},
{"name": "560"},
{"name": "561"},
{"name": "562"},
{"name": "563"},
{"name": "564"},
{"name": "565"},
{"name": "566"},
{"name": "567"},
{"name": "568"},
{"name": "569"},
{"name": "570"},
{"name": "571"},
{"name": "572"},
{"name": "573"},
{"name": "574"},
{"name": "575"},
{"name": "576"},
{"name": "577"},
{"name": "578"},
{"name": "579"},
{"name": "580"},
{"name": "581"},
{"name": "582"},
{"name": "583"},
{"name": "584"},
{"name": "585"},
{"name": "586"},
{"name": "587"},
{"name": "588"},
{"name": "589"},
{"name": "590"},
{"name": "591"},
{"name": "592"},
{"name": "593"},
{"name": "594"},
{"name": "595"},
{"name": "596"},
{"name": "597"},
{"name": "598"},
{"name": "599"},
{"name": "600"},
{"name": "601"},
{"name": "602"},
{"name": "603"},
{"name": "604"},
{"name": "605"},
{"name": "606"},
{"name": "607"},
{"name": "608"},
{"name": "609"},
{"name": "610"},
{"name": "611"},
{"name": "612"},
{"name": "613"},
{"name": "614"},
{"name": "615"},
{"name": "616"},
{"name": "617"},
{"name": "618"},
{"name": "619"},
{"name": "620"},
{"name": "621"},
{"name": "622"},
{"name": "623"},
{"name": "624"},
{"name": "625"},
{"name": "626"},
{"name": "627"},
{"name": "628"},
{"name": "629"},
{"name": "630"},
{"name": "631"},
{"name": "632"},
{"name": "633"},
{"name": "634"},
{"name": "635"},
{"name": "636"},
{"name": "637"},
{"name": "638"},
{"name": "639"},
{"name": "640"},
{"name": "641"},
{"name": "642"},
{"name": "643"},
{"name": "644"},
{"name": "645"},
{"name": "646"},
{"name": "647"},
{"name": "648"},
{"name": "649"},
{"name": "650"},
{"name": "651"},
{"name": "652"},
{"name": "653"},
{"name": "654"},
{"name": "655"},
{"name": "656"},
{"name": "657"},
{"name": "658"},
{"name": "659"},
{"name": "660"},
{"name": "661"},
{"name": "662"},
{"name": "663"},
{"name": "664"},
{"name": "665"},
{"name": "666"},
{"name": "667"},
{"name": "668"},
{"name": "669"},
{"name": "670"},
{"name": "671"},
{"name": "672"},
{"name": "673"},
{"name": "674"},
{"name": "675"},
{"name": "676"},
{"name": "677"},
{"name": "678"},
{"name": "679"},
{"name": "680"},
{"name": "681"},
{"name": "682"},
{"name": "683"},
{"name": "684"},
{"name": "685"},
{"name": "686"},
{"name": "687"},
{"name": "688"},
{"name": "689"},
{"name": "690"},
{"name": "691"},
{"name": "692"},
{"name": "693"},
{"name": "694"},
{"name": "695"},
{"name": "696"},
{"name": "697"},
{"name": "698"},
{"name": "699"},
{"name": "700"},
{"name": "701"},
{"name": "702"},
{"name": "703"},
{"name": "704"},
{"name": "705"},
{"name": "706"},
{"name": "707"},
{"name": "708"},
{"name": "709"},
{"name": "710"},
{"name": "711"},
{"name": "712"},
{"name": "713"},
{"name": "714"},
{"name": "715"},
{"name": "716"},
{"name": "717"},
{"name": "718"},
{"name": "719"},
{"name": "720"},
{"name": "721"},
{"name": "722"},
{"name": "723"},
{"name": "724"},
{"name": "725"},
{"name": "726"},
{"name": "727"},
{"name": "728"},
{"name": "729"},
{"name": "730"},
{"name": "731"},
{"name": "732"},
{"name": "733"},
{"name": "734"},
{"name": "735"},
{"name": "736"},
{"name": "737"},
{"name": "738"},
{"name": "739"},
{"name": "740"},
{"name": "741"},
{"name": "742"},
{"name": "743"},
{"name": "744"},
{"name": "745"},
{"name": "746"},
{"name": "747"},
{"name": "748"},
{"name": "749"},
{"name": "750"},
{"name": "751"},
{"name": "752"},
{"name": "753"},
{"name": "754"},
{"name": "755"},
{"name": "756"},
{"name": "757"},
{"name": "758"},
{"name": "759"},
{"name": "760"},
{"name": "761"},
{"name": "762"},
{"name": "763"},
{"name": "764"},
{"name": "765"},
{"name": "766"},
{"name": "767"},
{"name": "768"},
{"name": "769"},
{"name": "770"},
{"name": "771"},
{"name": "772"},
{"name": "773"},
{"name": "774"},
{"name": "775"},
{"name": "776"},
{"name": "777"},
{"name": "778"},
{"name": "779"},
{"name": "780"},
{"name": "781"},
{"name": "782"},
{"name": "783"},
{"name": "784"},
{"name": "785"},
{"name": "786"},
{"name": "787"},
{"name": "788"},
{"name": "789"},
{"name": "790"},
{"name": "791"},
{"name": "792"},
{"name": "793"},
{"name": "794"},
{"name": "795"},
{"name": "796"},
{"name": "797"},
{"name": "798"},
{"name": "799"},
{"name": "800"},
{"name": "801"},
{"name": "802"},
{"name": "803"},
{"name": "804"},
{"name": "805"},
{"name": "806"},
{"name": "807"},
{"name": "808"},
{"name": "809"},
{"name": "810"},
{"name": "811"},
{"name": "812"},
{"name": "813"},
{"name": "814"},
{"name": "815"},
{"name": "816"},
{"name": "817"},
{"name": "818"},
{"name": "819"},
{"name": "820"},
{"name": "821"},
{"name": "822"},
{"name": "823"},
{"name": "824"},
{"name": "825"},
{"name": "826"},
{"name": "827"},
{"name": "828"},
{"name": "829"},
{"name": "830"},
{"name": "831"},
{"name": "832"},
{"name": "833"},
{"name": "834"},
{"name": "835"},
{"name": "836"},
{"name": "837"},
{"name": "838"},
{"name": "839"},
{"name": "840"},
{"name": "841"},
{"name": "842"},
{"name": "843"},
{"name": "844"},
{"name": "845"},
{"name": "846"},
{"name": "847"},
{"name": "848"},
{"name": "849"},
{"name": "850"},
{"name": "851"},
{"name": "852"},
{"name": "853"},
{"name": "854"},
{"name": "855"},
{"name": "856"},
{"name": "857"},
{"name": "858"},
{"name": "859"},
{"name": "860"},
{"name": "861"},
{"name": "862"},
{"name": "863"},
{"name": "864"},
{"name": "865"},
{"name": "866"},
{"name": "867"},
{"name": "868"},
{"name": "869"},
{"name": "870"},
{"name": "871"},
{"name": "872"},
{"name": "873"},
{"name": "874"},
{"name": "875"},
{"name": "876"},
{"name": "877"},
{"name": "878"},
{"name": "879"},
{"name": "880"},
{"name": "881"},
{"name": "882"},
{"name": "883"},
{"name": "884"},
{"name": "885"},
{"name": "886"},
{"name": "887"},
{"name": "888"},
{"name": "889"},
{"name": "890"},
{"name": "891"},
{"name": "892"},
{"name": "893"},
{"name": "894"},
{"name": "895"},
{"name": "896"},
{"name": "897"},
{"name": "898"},
{"name": "899"},
{"name": "900"},
{"name": "901"},
{"name": "902"},
{"name": "903"},
{"name": "904"},
{"name": "905"},
{"name": "906"},
{"name": "907"},
{"name": "908"},
{"name": "909"},
{"name": "910"},
{"name": "911"},
{"name": "912"},
{"name": "913"},
{"name": "914"},
{"name": "915"},
{"name": "916"},
{"name": "917"},
{"name": "918"},
{"name": "919"},
{"name": "920"},
{"name": "921"},
{"name": "922"},
{"name": "923"},
{"name": "924"},
{"name": "925"},
{"name": "926"},
{"name": "927"},
{"name": "928"},
{"name": "929"},
{"name": "930"},
{"name": "931"},
{"name": "932"},
{"name": "933"},
{"name": "934"},
{"name": "935"},
{"name": "936"},
{"name": "937"},
{"name": "938"},
{"name": "939"},
{"name": "940"},
{"name": "941"},
{"name": "942"},
{"name": "943"},
{"name": "944"},
{"name": "945"},
{"name": "946"},
{"name": "947"},
{"name": "948"},
{"name": "949"},
{"name": "950"},
{"name": "951"},
{"name": "952"},
{"name": "953"},
{"name": "954"},
{"name": "955"},
{"name": "956"},
{"name": "957"},
{"name": "958"},
{"name": "959"},
{"name": "960"},
{"name": "961"},
{"name": "962"},
{"name": "963"},
{"name": "964"},
{"name": "965"},
{"name": "966"},
{"name": "967"},
{"name": "968"},
{"name": "969"},
{"name": "970"}
],
"links": [
{"source": 0, "target": 211, "value": 0.04},
{"source": 0, "target": 630, "value": 0.05},
{"source": 0, "target": 883, "value": 0.07},
{"source": 0, "target": 125, "value": 0.08},
{"source": 0, "target": 116, "value": 0.09},
{"source": 0, "target": 315, "value": 0.34},
{"source": 0, "target": 741, "value": 0.53},
{"source": 0, "target": 451, "value": 0.53},
{"source": 0, "target": 398, "value": 0.53},
{"source": 0, "target": 397, "value": 0.53},
{"source": 0, "target": 373, "value": 0.53},
{"source": 0, "target": 130, "value": 0.53},
{"source": 1, "target": 895, "value": 0.04},
{"source": 1, "target": 794, "value": 0.04},
{"source": 1, "target": 358, "value": 0.34},
{"source": 1, "target": 356, "value": 0.34},
{"source": 1, "target": 479, "value": 0.53},
{"source": 1, "target": 410, "value": 0.53},
{"source": 1, "target": 196, "value": 0.53},
{"source": 2, "target": 297, "value": 0.07},
{"source": 2, "target": 803, "value": 0.08},
{"source": 2, "target": 521, "value": 0.34},
{"source": 2, "target": 512, "value": 0.53},
{"source": 2, "target": 419, "value": 0.53},
{"source": 2, "target": 115, "value": 0.53},
{"source": 3, "target": 843, "value": 0.17},
{"source": 4, "target": 948, "value": 0.04},
{"source": 4, "target": 861, "value": 0.07},
{"source": 4, "target": 584, "value": 0.20},
{"source": 4, "target": 352, "value": 0.26},
{"source": 4, "target": 254, "value": 0.34},
{"source": 4, "target": 765, "value": 0.53},
{"source": 4, "target": 715, "value": 0.53},
{"source": 4, "target": 463, "value": 0.53},
{"source": 4, "target": 418, "value": 0.53},
{"source": 4, "target": 252, "value": 0.53},
{"source": 5, "target": 652, "value": 0.05},
{"source": 5, "target": 346, "value": 0.53},
{"source": 5, "target": 140, "value": 0.53},
{"source": 6, "target": 577, "value": 0.15},
{"source": 6, "target": 536, "value": 0.53},
{"source": 6, "target": 466, "value": 0.53},
{"source": 6, "target": 298, "value": 0.53},
{"source": 7, "target": 938, "value": 0.11},
{"source": 7, "target": 321, "value": 0.34},
{"source": 7, "target": 537, "value": 0.53},
{"source": 7, "target": 517, "value": 0.53},
{"source": 7, "target": 281, "value": 0.53},
{"source": 8, "target": 735, "value": 0.05},
{"source": 8, "target": 458, "value": 0.11},
{"source": 8, "target": 360, "value": 0.20},
{"source": 8, "target": 956, "value": 0.26},
{"source": 8, "target": 507, "value": 0.53},
{"source": 8, "target": 485, "value": 0.53},
{"source": 8, "target": 474, "value": 0.53},
{"source": 8, "target": 471, "value": 0.53},
{"source": 9, "target": 257, "value": 0.03},
{"source": 9, "target": 905, "value": 0.05},
{"source": 9, "target": 30, "value": 0.06},
{"source": 9, "target": 875, "value": 0.07},
{"source": 9, "target": 366, "value": 0.08},
{"source": 9, "target": 59, "value": 0.34},
{"source": 9, "target": 84, "value": 0.53},
{"source": 10, "target": 675, "value": 0.07},
{"source": 10, "target": 529, "value": 0.53},
{"source": 10, "target": 414, "value": 0.53},
{"source": 10, "target": 357, "value": 0.53},
{"source": 11, "target": 952, "value": 0.03},
{"source": 11, "target": 400, "value": 0.11},
{"source": 11, "target": 923, "value": 0.53},
{"source": 11, "target": 477, "value": 0.53},
{"source": 11, "target": 275, "value": 0.53},
{"source": 12, "target": 648, "value": 0.03},
{"source": 12, "target": 597, "value": 0.05},
{"source": 12, "target": 306, "value": 0.34},
{"source": 13, "target": 301, "value": 0.07},
{"source": 14, "target": 624, "value": 0.03},
{"source": 14, "target": 957, "value": 0.05},
{"source": 14, "target": 685, "value": 0.53},
{"source": 14, "target": 467, "value": 0.53},
{"source": 15, "target": 676, "value": 0.15},
{"source": 16, "target": 712, "value": 0.04},
{"source": 16, "target": 494, "value": 0.53},
{"source": 17, "target": 630, "value": 0.05},
{"source": 18, "target": 244, "value": 0.07},
{"source": 18, "target": 461, "value": 0.34},
{"source": 19, "target": 406, "value": 0.04},
{"source": 19, "target": 239, "value": 0.20},
{"source": 19, "target": 277, "value": 0.53},
{"source": 20, "target": 195, "value": 0.04},
{"source": 20, "target": 819, "value": 0.04},
{"source": 20, "target": 600, "value": 0.05},
{"source": 20, "target": 255, "value": 0.15},
{"source": 20, "target": 516, "value": 0.53},
{"source": 21, "target": 172, "value": 0.03},
{"source": 21, "target": 326, "value": 0.08},
{"source": 21, "target": 154, "value": 0.08},
{"source": 21, "target": 188, "value": 0.17},
{"source": 21, "target": 192, "value": 0.53},
{"source": 22, "target": 394, "value": 0.08},
{"source": 23, "target": 914, "value": 0.05},
{"source": 23, "target": 429, "value": 0.53},
{"source": 24, "target": 195, "value": 0.05},
{"source": 24, "target": 340, "value": 0.53},
{"source": 25, "target": 602, "value": 0.08},
{"source": 25, "target": 36, "value": 0.53},
{"source": 26, "target": 312, "value": 0.05},
{"source": 27, "target": 87, "value": 0.05},
{"source": 28, "target": 65, "value": 0.03},
{"source": 28, "target": 712, "value": 0.04},
{"source": 28, "target": 304, "value": 0.36},
{"source": 29, "target": 602, "value": 0.06},
{"source": 31, "target": 653, "value": 0.06},
{"source": 31, "target": 341, "value": 0.17},
{"source": 31, "target": 110, "value": 0.34},
{"source": 32, "target": 607, "value": 0.03},
{"source": 32, "target": 181, "value": 0.03},
{"source": 32, "target": 289, "value": 0.04},
{"source": 32, "target": 249, "value": 0.10},
{"source": 32, "target": 437, "value": 0.53},
{"source": 33, "target": 257, "value": 0.05},
{"source": 34, "target": 643, "value": 0.07},
{"source": 35, "target": 312, "value": 0.08},
{"source": 37, "target": 619, "value": 0.03},
{"source": 38, "target": 709, "value": 0.07},
{"source": 38, "target": 514, "value": 0.53},
{"source": 40, "target": 872, "value": 0.06},
{"source": 40, "target": 557, "value": 0.27},
{"source": 40, "target": 480, "value": 0.34},
{"source": 40, "target": 511, "value": 0.53},
{"source": 41, "target": 657, "value": 0.04},
{"source": 41, "target": 599, "value": 0.20},
{"source": 41, "target": 608, "value": 0.53},
{"source": 42, "target": 704, "value": 0.07},
{"source": 43, "target": 712, "value": 0.11},
{"source": 44, "target": 938, "value": 0.05},
{"source": 45, "target": 394, "value": 0.04},
{"source": 45, "target": 929, "value": 0.06},
{"source": 45, "target": 510, "value": 0.53},
{"source": 46, "target": 375, "value": 0.05},
{"source": 47, "target": 648, "value": 0.03},
{"source": 48, "target": 648, "value": 0.04},
{"source": 48, "target": 431, "value": 0.05},
{"source": 49, "target": 513, "value": 0.06},
{"source": 51, "target": 528, "value": 0.04},
{"source": 52, "target": 955, "value": 0.05},
{"source": 54, "target": 166, "value": 0.06},
{"source": 55, "target": 781, "value": 0.08},
{"source": 57, "target": 888, "value": 0.17},
{"source": 58, "target": 730, "value": 0.05},
{"source": 58, "target": 486, "value": 0.05},
{"source": 60, "target": 416, "value": 0.07},
{"source": 60, "target": 798, "value": 0.21},
{"source": 61, "target": 67, "value": 0.03},
{"source": 61, "target": 952, "value": 0.03},
{"source": 61, "target": 329, "value": 0.06},
{"source": 61, "target": 387, "value": 0.08},
{"source": 62, "target": 909, "value": 0.08},
{"source": 63, "target": 943, "value": 0.09},
{"source": 64, "target": 712, "value": 0.05},
{"source": 64, "target": 425, "value": 0.20},
{"source": 64, "target": 488, "value": 0.34},
{"source": 65, "target": 274, "value": 0.05},
{"source": 65, "target": 612, "value": 0.08},
{"source": 65, "target": 78, "value": 0.14},
{"source": 66, "target": 172, "value": 0.06},
{"source": 66, "target": 820, "value": 0.08},
{"source": 66, "target": 367, "value": 0.53},
{"source": 67, "target": 91, "value": 0.03},
{"source": 67, "target": 781, "value": 0.05},
{"source": 67, "target": 915, "value": 0.11},
{"source": 67, "target": 408, "value": 0.26},
{"source": 68, "target": 712, "value": 0.04},
{"source": 68, "target": 587, "value": 0.04},
{"source": 68, "target": 821, "value": 0.05},
{"source": 68, "target": 829, "value": 0.06},
{"source": 68, "target": 285, "value": 0.08},
{"source": 68, "target": 265, "value": 0.17},
{"source": 68, "target": 219, "value": 0.20},
{"source": 68, "target": 817, "value": 0.34},
{"source": 68, "target": 347, "value": 0.34},
{"source": 69, "target": 826, "value": 0.04},
{"source": 69, "target": 330, "value": 0.04},
{"source": 69, "target": 946, "value": 0.10},
{"source": 69, "target": 97, "value": 0.17},
{"source": 69, "target": 151, "value": 0.17},
{"source": 70, "target": 128, "value": 0.26},
{"source": 71, "target": 643, "value": 0.10},
{"source": 72, "target": 639, "value": 0.06},
{"source": 74, "target": 868, "value": 0.05},
{"source": 74, "target": 770, "value": 0.05},
{"source": 74, "target": 314, "value": 0.07},
{"source": 75, "target": 648, "value": 0.05},
{"source": 76, "target": 604, "value": 0.04},
{"source": 76, "target": 648, "value": 0.04},
{"source": 76, "target": 768, "value": 0.04},
{"source": 76, "target": 160, "value": 0.05},
{"source": 76, "target": 717, "value": 0.05},
{"source": 76, "target": 569, "value": 0.08},
{"source": 76, "target": 424, "value": 0.17},
{"source": 77, "target": 581, "value": 0.03},
{"source": 77, "target": 694, "value": 0.03},
{"source": 77, "target": 405, "value": 0.15},
{"source": 79, "target": 301, "value": 0.04},
{"source": 79, "target": 568, "value": 0.06},
{"source": 80, "target": 762, "value": 0.04},
{"source": 80, "target": 121, "value": 0.05},
{"source": 80, "target": 911, "value": 0.11},
{"source": 81, "target": 895, "value": 0.05},
{"source": 82, "target": 267, "value": 0.15},
{"source": 83, "target": 91, "value": 0.05},
{"source": 86, "target": 712, "value": 0.04},
{"source": 86, "target": 736, "value": 0.07},
{"source": 86, "target": 225, "value": 0.26},
{"source": 87, "target": 896, "value": 0.04},
{"source": 87, "target": 388, "value": 0.09},
{"source": 87, "target": 287, "value": 0.20},
{"source": 88, "target": 653, "value": 0.06},
{"source": 89, "target": 256, "value": 0.04},
{"source": 89, "target": 965, "value": 0.06},
{"source": 90, "target": 662, "value": 0.09},
{"source": 91, "target": 113, "value": 0.03},
{"source": 91, "target": 394, "value": 0.04},
{"source": 91, "target": 862, "value": 0.04},
{"source": 91, "target": 788, "value": 0.05},
{"source": 92, "target": 827, "value": 0.11},
{"source": 93, "target": 859, "value": 0.07},
{"source": 94, "target": 363, "value": 0.05},
{"source": 95, "target": 301, "value": 0.04},
{"source": 96, "target": 301, "value": 0.04},
{"source": 98, "target": 221, "value": 0.04},
{"source": 98, "target": 376, "value": 0.26},
{"source": 99, "target": 195, "value": 0.05},
{"source": 99, "target": 508, "value": 0.53},
{"source": 100, "target": 652, "value": 0.04},
{"source": 100, "target": 317, "value": 0.05},
{"source": 100, "target": 874, "value": 0.26},
{"source": 101, "target": 181, "value": 0.05},
{"source": 102, "target": 712, "value": 0.04},
{"source": 102, "target": 186, "value": 0.17},
{"source": 103, "target": 369, "value": 0.11},
{"source": 105, "target": 653, "value": 0.06},
{"source": 105, "target": 490, "value": 0.34},
{"source": 106, "target": 910, "value": 0.03},
{"source": 106, "target": 896, "value": 0.03},
{"source": 106, "target": 181, "value": 0.04},
{"source": 106, "target": 868, "value": 0.04},
{"source": 106, "target": 575, "value": 0.04},
{"source": 106, "target": 136, "value": 0.04},
{"source": 106, "target": 707, "value": 0.06},
{"source": 106, "target": 963, "value": 0.12},
{"source": 107, "target": 301, "value": 0.05},
{"source": 107, "target": 210, "value": 0.06},
{"source": 108, "target": 653, "value": 0.08},
{"source": 109, "target": 955, "value": 0.13},
{"source": 111, "target": 729, "value": 0.03},
{"source": 111, "target": 323, "value": 0.17},
{"source": 111, "target": 497, "value": 0.34},
{"source": 111, "target": 377, "value": 0.53},
{"source": 112, "target": 465, "value": 0.05},
{"source": 113, "target": 181, "value": 0.03},
{"source": 113, "target": 873, "value": 0.03},
{"source": 113, "target": 865, "value": 0.05},
{"source": 113, "target": 515, "value": 0.26},
{"source": 114, "target": 301, "value": 0.03},
{"source": 114, "target": 901, "value": 0.05},
{"source": 114, "target": 867, "value": 0.10},
{"source": 117, "target": 712, "value": 0.05},
{"source": 118, "target": 811, "value": 0.13},
{"source": 119, "target": 401, "value": 0.04},
{"source": 120, "target": 625, "value": 0.14},
{"source": 122, "target": 762, "value": 0.07},
{"source": 122, "target": 324, "value": 0.13},
{"source": 123, "target": 195, "value": 0.04},
{"source": 123, "target": 653, "value": 0.04},
{"source": 123, "target": 887, "value": 0.06},
{"source": 123, "target": 636, "value": 0.20},
{"source": 124, "target": 623, "value": 0.05},
{"source": 124, "target": 282, "value": 0.21},
{"source": 124, "target": 403, "value": 0.26},
{"source": 125, "target": 291, "value": 0.36},
{"source": 126, "target": 465, "value": 0.08},
{"source": 127, "target": 351, "value": 0.11},
{"source": 128, "target": 827, "value": 0.06},
{"source": 128, "target": 711, "value": 0.17},
{"source": 129, "target": 674, "value": 0.10},
{"source": 131, "target": 966, "value": 0.04},
{"source": 132, "target": 868, "value": 0.06},
{"source": 133, "target": 630, "value": 0.34},
{"source": 134, "target": 581, "value": 0.03},
{"source": 135, "target": 866, "value": 0.11},
{"source": 136, "target": 917, "value": 0.08},
{"source": 136, "target": 818, "value": 0.26},
{"source": 137, "target": 669, "value": 0.04},
{"source": 138, "target": 215, "value": 0.11},
{"source": 139, "target": 578, "value": 0.05},
{"source": 141, "target": 654, "value": 0.13},
{"source": 143, "target": 865, "value": 0.26},
{"source": 144, "target": 465, "value": 0.34},
{"source": 145, "target": 406, "value": 0.06},
{"source": 146, "target": 195, "value": 0.11},
{"source": 147, "target": 695, "value": 0.04},
{"source": 148, "target": 955, "value": 0.06},
{"source": 149, "target": 401, "value": 0.14},
{"source": 150, "target": 653, "value": 0.08},
{"source": 152, "target": 895, "value": 0.34},
{"source": 153, "target": 960, "value": 0.13},
{"source": 154, "target": 444, "value": 0.20},
{"source": 155, "target": 695, "value": 0.04},
{"source": 155, "target": 452, "value": 0.34},
{"source": 156, "target": 694, "value": 0.07},
{"source": 157, "target": 859, "value": 0.10},
{"source": 158, "target": 653, "value": 0.09},
{"source": 159, "target": 280, "value": 0.06},
{"source": 160, "target": 831, "value": 0.08},
{"source": 161, "target": 643, "value": 0.34},
{"source": 162, "target": 712, "value": 0.04},
{"source": 162, "target": 462, "value": 0.15},
{"source": 162, "target": 481, "value": 0.26},
{"source": 162, "target": 170, "value": 0.34},
{"source": 163, "target": 577, "value": 0.05},
{"source": 164, "target": 623, "value": 0.04},
{"source": 165, "target": 721, "value": 0.15},
{"source": 166, "target": 712, "value": 0.03},
{"source": 166, "target": 224, "value": 0.04},
{"source": 166, "target": 892, "value": 0.05},
{"source": 166, "target": 179, "value": 0.06},
{"source": 166, "target": 571, "value": 0.07},
{"source": 166, "target": 338, "value": 0.09},
{"source": 167, "target": 652, "value": 0.06},
{"source": 169, "target": 712, "value": 0.11},
{"source": 171, "target": 809, "value": 0.26},
{"source": 172, "target": 966, "value": 0.03},
{"source": 172, "target": 712, "value": 0.03},
{"source": 172, "target": 443, "value": 0.04},
{"source": 172, "target": 710, "value": 0.04},
{"source": 172, "target": 183, "value": 0.05},
{"source": 172, "target": 634, "value": 0.05},
{"source": 172, "target": 487, "value": 0.34},
{"source": 173, "target": 301, "value": 0.04},
{"source": 173, "target": 383, "value": 0.04},
{"source": 173, "target": 227, "value": 0.07},
{"source": 174, "target": 824, "value": 0.21},
{"source": 175, "target": 762, "value": 0.04},
{"source": 175, "target": 964, "value": 0.05},
{"source": 176, "target": 960, "value": 0.20},
{"source": 177, "target": 577, "value": 0.06},
{"source": 177, "target": 353, "value": 0.08},
{"source": 177, "target": 365, "value": 0.20},
{"source": 177, "target": 935, "value": 0.26},
{"source": 177, "target": 263, "value": 0.34},
{"source": 178, "target": 855, "value": 0.07},
{"source": 180, "target": 712, "value": 0.04},
{"source": 181, "target": 648, "value": 0.03},
{"source": 181, "target": 786, "value": 0.04},
{"source": 181, "target": 628, "value": 0.04},
{"source": 181, "target": 456, "value": 0.04},
{"source": 181, "target": 718, "value": 0.05},
{"source": 181, "target": 748, "value": 0.05},
{"source": 181, "target": 381, "value": 0.06},
{"source": 182, "target": 895, "value": 0.07},
{"source": 184, "target": 955, "value": 0.13},
{"source": 185, "target": 611, "value": 0.08},
{"source": 187, "target": 927, "value": 0.08},
{"source": 189, "target": 882, "value": 0.26},
{"source": 190, "target": 348, "value": 0.11},
{"source": 191, "target": 483, "value": 0.37},
{"source": 193, "target": 927, "value": 0.17},
{"source": 194, "target": 927, "value": 0.06},
{"source": 195, "target": 394, "value": 0.03},
{"source": 195, "target": 627, "value": 0.04},
{"source": 195, "target": 363, "value": 0.04},
{"source": 195, "target": 953, "value": 0.04},
{"source": 195, "target": 266, "value": 0.05},
{"source": 195, "target": 579, "value": 0.06},
{"source": 195, "target": 679, "value": 0.17},
{"source": 197, "target": 393, "value": 0.06},
{"source": 197, "target": 687, "value": 0.07},
{"source": 197, "target": 518, "value": 0.20},
{"source": 198, "target": 351, "value": 0.06},
{"source": 199, "target": 941, "value": 0.18},
{"source": 200, "target": 221, "value": 0.08},
{"source": 201, "target": 895, "value": 0.06},
{"source": 202, "target": 301, "value": 0.06},
{"source": 204, "target": 301, "value": 0.04},
{"source": 204, "target": 664, "value": 0.05},
{"source": 204, "target": 776, "value": 0.08},
{"source": 206, "target": 939, "value": 0.05},
{"source": 208, "target": 782, "value": 0.06},
{"source": 209, "target": 805, "value": 0.04},
{"source": 211, "target": 667, "value": 0.04},
{"source": 211, "target": 782, "value": 0.05},
{"source": 211, "target": 796, "value": 0.06},
{"source": 211, "target": 858, "value": 0.06},
{"source": 211, "target": 359, "value": 0.08},
{"source": 211, "target": 422, "value": 0.34},
{"source": 212, "target": 757, "value": 0.34},
{"source": 213, "target": 648, "value": 0.13},
{"source": 214, "target": 735, "value": 0.04},
{"source": 214, "target": 311, "value": 0.27},
{"source": 215, "target": 955, "value": 0.06},
{"source": 216, "target": 966, "value": 0.17},
{"source": 217, "target": 648, "value": 0.04},
{"source": 218, "target": 401, "value": 0.08},
{"source": 220, "target": 619, "value": 0.04},
{"source": 221, "target": 813, "value": 0.03},
{"source": 221, "target": 348, "value": 0.03},
{"source": 221, "target": 960, "value": 0.04},
{"source": 221, "target": 906, "value": 0.04},
{"source": 221, "target": 654, "value": 0.04},
{"source": 221, "target": 805, "value": 0.04},
{"source": 221, "target": 844, "value": 0.04},
{"source": 221, "target": 757, "value": 0.06},
{"source": 221, "target": 949, "value": 0.07},
{"source": 221, "target": 455, "value": 0.08},
{"source": 221, "target": 310, "value": 0.13},
{"source": 222, "target": 648, "value": 0.05},
{"source": 223, "target": 691, "value": 0.17},
{"source": 224, "target": 235, "value": 0.11},
{"source": 226, "target": 966, "value": 0.10},
{"source": 228, "target": 297, "value": 0.04},
{"source": 228, "target": 859, "value": 0.04},
{"source": 228, "target": 737, "value": 0.04},
{"source": 228, "target": 294, "value": 0.05},
{"source": 228, "target": 879, "value": 0.06},
{"source": 230, "target": 297, "value": 0.05},
{"source": 231, "target": 898, "value": 0.13},
{"source": 232, "target": 586, "value": 0.04},
{"source": 232, "target": 692, "value": 0.04},
{"source": 233, "target": 854, "value": 0.05},
{"source": 233, "target": 344, "value": 0.05},
{"source": 234, "target": 301, "value": 0.06},
{"source": 236, "target": 938, "value": 0.11},
{"source": 237, "target": 671, "value": 0.26},
{"source": 238, "target": 855, "value": 0.06},
{"source": 240, "target": 319, "value": 0.09},
{"source": 241, "target": 301, "value": 0.08},
{"source": 242, "target": 813, "value": 0.06},
{"source": 243, "target": 406, "value": 0.05},
{"source": 243, "target": 436, "value": 0.17},
{"source": 244, "target": 648, "value": 0.03},
{"source": 244, "target": 735, "value": 0.03},
{"source": 244, "target": 272, "value": 0.09},
{"source": 245, "target": 712, "value": 0.04},
{"source": 246, "target": 637, "value": 0.08},
{"source": 247, "target": 955, "value": 0.14},
{"source": 248, "target": 648, "value": 0.07},
{"source": 250, "target": 620, "value": 0.03},
{"source": 250, "target": 966, "value": 0.04},
{"source": 250, "target": 859, "value": 0.04},
{"source": 250, "target": 826, "value": 0.04},
{"source": 250, "target": 811, "value": 0.06},
{"source": 251, "target": 791, "value": 0.06},
{"source": 253, "target": 348, "value": 0.09},
{"source": 256, "target": 301, "value": 0.03},
{"source": 256, "target": 631, "value": 0.05},
{"source": 256, "target": 482, "value": 0.06},
{"source": 256, "target": 286, "value": 0.06},
{"source": 256, "target": 439, "value": 0.06},
{"source": 256, "target": 808, "value": 0.07},
{"source": 257, "target": 895, "value": 0.03},
{"source": 257, "target": 709, "value": 0.03},
{"source": 257, "target": 938, "value": 0.04},
{"source": 257, "target": 784, "value": 0.04},
{"source": 257, "target": 320, "value": 0.04},
{"source": 257, "target": 857, "value": 0.04},
{"source": 257, "target": 837, "value": 0.04},
{"source": 257, "target": 382, "value": 0.07},
{"source": 258, "target": 723, "value": 0.26},
{"source": 259, "target": 960, "value": 0.17},
{"source": 260, "target": 815, "value": 0.04},
{"source": 261, "target": 966, "value": 0.04},
{"source": 261, "target": 730, "value": 0.04},
{"source": 261, "target": 572, "value": 0.05},
{"source": 261, "target": 701, "value": 0.20},
{"source": 261, "target": 415, "value": 0.34},
{"source": 262, "target": 896, "value": 0.04},
{"source": 264, "target": 955, "value": 0.14},
{"source": 266, "target": 438, "value": 0.17},
{"source": 267, "target": 607, "value": 0.03},
{"source": 267, "target": 729, "value": 0.03},
{"source": 267, "target": 611, "value": 0.03},
{"source": 267, "target": 577, "value": 0.03},
{"source": 267, "target": 714, "value": 0.03},
{"source": 267, "target": 815, "value": 0.04},
{"source": 267, "target": 661, "value": 0.04},
{"source": 267, "target": 791, "value": 0.04},
{"source": 267, "target": 839, "value": 0.11},
{"source": 267, "target": 945, "value": 0.11},
{"source": 267, "target": 445, "value": 0.15},
{"source": 267, "target": 493, "value": 0.20},
{"source": 267, "target": 484, "value": 0.26},
{"source": 267, "target": 795, "value": 0.34},
{"source": 268, "target": 909, "value": 0.26},
{"source": 269, "target": 712, "value": 0.04},
{"source": 270, "target": 301, "value": 0.05},
{"source": 271, "target": 854, "value": 0.20},
{"source": 273, "target": 735, "value": 0.04},
{"source": 276, "target": 704, "value": 0.07},
{"source": 279, "target": 787, "value": 0.13},
{"source": 280, "target": 667, "value": 0.05},
{"source": 280, "target": 840, "value": 0.06},
{"source": 284, "target": 859, "value": 0.09},
{"source": 288, "target": 652, "value": 0.04},
{"source": 289, "target": 652, "value": 0.03},
{"source": 289, "target": 742, "value": 0.04},
{"source": 289, "target": 303, "value": 0.09},
{"source": 290, "target": 578, "value": 0.21},
{"source": 292, "target": 694, "value": 0.05},
{"source": 293, "target": 648, "value": 0.03},
{"source": 293, "target": 909, "value": 0.04},
{"source": 293, "target": 393, "value": 0.04},
{"source": 293, "target": 420, "value": 0.04},
{"source": 293, "target": 640, "value": 0.09},
{"source": 295, "target": 872, "value": 0.34},
{"source": 296, "target": 566, "value": 0.26},
{"source": 299, "target": 906, "value": 0.09},
{"source": 300, "target": 578, "value": 0.05},
{"source": 301, "target": 955, "value": 0.03},
{"source": 301, "target": 528, "value": 0.03},
{"source": 301, "target": 578, "value": 0.03},
{"source": 301, "target": 375, "value": 0.03},
{"source": 301, "target": 754, "value": 0.03},
{"source": 301, "target": 644, "value": 0.03},
{"source": 301, "target": 348, "value": 0.04},
{"source": 301, "target": 392, "value": 0.04},
{"source": 301, "target": 706, "value": 0.04},
{"source": 301, "target": 669, "value": 0.04},
{"source": 301, "target": 513, "value": 0.04},
{"source": 301, "target": 764, "value": 0.04},
{"source": 301, "target": 942, "value": 0.04},
{"source": 301, "target": 755, "value": 0.05},
{"source": 301, "target": 860, "value": 0.05},
{"source": 301, "target": 849, "value": 0.05},
{"source": 301, "target": 907, "value": 0.05},
{"source": 301, "target": 880, "value": 0.05},
{"source": 301, "target": 954, "value": 0.05},
{"source": 301, "target": 940, "value": 0.06},
{"source": 301, "target": 440, "value": 0.06},
{"source": 301, "target": 846, "value": 0.06},
{"source": 302, "target": 330, "value": 0.15},
{"source": 305, "target": 446, "value": 0.05},
{"source": 305, "target": 852, "value": 0.05},
{"source": 308, "target": 344, "value": 0.05},
{"source": 312, "target": 320, "value": 0.05},
{"source": 313, "target": 783, "value": 0.15},
{"source": 316, "target": 895, "value": 0.07},
{"source": 318, "target": 578, "value": 0.04},
{"source": 319, "target": 737, "value": 0.06},
{"source": 320, "target": 364, "value": 0.05},
{"source": 320, "target": 336, "value": 0.07},
{"source": 322, "target": 959, "value": 0.07},
{"source": 325, "target": 375, "value": 0.05},
{"source": 328, "target": 794, "value": 0.53},
{"source": 330, "target": 790, "value": 0.05},
{"source": 330, "target": 848, "value": 0.05},
{"source": 330, "target": 416, "value": 0.05},
{"source": 330, "target": 968, "value": 0.10},
{"source": 331, "target": 652, "value": 0.04},
{"source": 331, "target": 413, "value": 0.09},
{"source": 333, "target": 779, "value": 0.36},
{"source": 334, "target": 895, "value": 0.26},
{"source": 335, "target": 575, "value": 0.09},
{"source": 337, "target": 783, "value": 0.21},
{"source": 338, "target": 472, "value": 0.34},
{"source": 339, "target": 790, "value": 0.05},
{"source": 339, "target": 759, "value": 0.53},
{"source": 342, "target": 712, "value": 0.15},
{"source": 343, "target": 952, "value": 0.18},
{"source": 344, "target": 895, "value": 0.03},
{"source": 344, "target": 864, "value": 0.06},
{"source": 345, "target": 607, "value": 0.14},
{"source": 349, "target": 833, "value": 0.17},
{"source": 350, "target": 767, "value": 0.20},
{"source": 351, "target": 607, "value": 0.03},
{"source": 351, "target": 855, "value": 0.04},
{"source": 351, "target": 775, "value": 0.04},
{"source": 351, "target": 943, "value": 0.05},
{"source": 351, "target": 368, "value": 0.06},
{"source": 351, "target": 434, "value": 0.15},
{"source": 354, "target": 783, "value": 0.04},
{"source": 355, "target": 613, "value": 0.27},
{"source": 361, "target": 878, "value": 0.09},
{"source": 362, "target": 960, "value": 0.10},
{"source": 363, "target": 934, "value": 0.13},
{"source": 364, "target": 556, "value": 0.26},
{"source": 369, "target": 824, "value": 0.04},
{"source": 370, "target": 658, "value": 0.26},
{"source": 372, "target": 891, "value": 0.36},
{"source": 374, "target": 528, "value": 0.20},
{"source": 375, "target": 589, "value": 0.05},
{"source": 375, "target": 478, "value": 0.09},
{"source": 378, "target": 949, "value": 0.34},
{"source": 379, "target": 966, "value": 0.10},
{"source": 380, "target": 659, "value": 0.34},
{"source": 383, "target": 932, "value": 0.07},
{"source": 384, "target": 671, "value": 0.11},
{"source": 385, "target": 952, "value": 0.08},
{"source": 389, "target": 719, "value": 0.13},
{"source": 390, "target": 604, "value": 0.06},
{"source": 390, "target": 851, "value": 0.13},
{"source": 391, "target": 962, "value": 0.17},
{"source": 394, "target": 719, "value": 0.05},
{"source": 394, "target": 897, "value": 0.05},
{"source": 394, "target": 594, "value": 0.06},
{"source": 395, "target": 948, "value": 0.20},
{"source": 396, "target": 652, "value": 0.05},
{"source": 399, "target": 623, "value": 0.05},
{"source": 401, "target": 653, "value": 0.04},
{"source": 401, "target": 623, "value": 0.04},
{"source": 402, "target": 588, "value": 0.36},
{"source": 404, "target": 730, "value": 0.08},
{"source": 406, "target": 528, "value": 0.03},
{"source": 406, "target": 662, "value": 0.05},
{"source": 406, "target": 920, "value": 0.10},
{"source": 411, "target": 465, "value": 0.05},
{"source": 411, "target": 837, "value": 0.05},
{"source": 412, "target": 652, "value": 0.06},
{"source": 417, "target": 699, "value": 0.26},
{"source": 421, "target": 855, "value": 0.08},
{"source": 423, "target": 902, "value": 0.26},
{"source": 426, "target": 689, "value": 0.34},
{"source": 428, "target": 649, "value": 0.17},
{"source": 430, "target": 906, "value": 0.21},
{"source": 441, "target": 764, "value": 0.07},
{"source": 442, "target": 707, "value": 0.26},
{"source": 444, "target": 489, "value": 0.26},
{"source": 447, "target": 648, "value": 0.05},
{"source": 448, "target": 465, "value": 0.03},
{"source": 448, "target": 928, "value": 0.08},
{"source": 449, "target": 600, "value": 0.17},
{"source": 454, "target": 959, "value": 0.37},
{"source": 457, "target": 854, "value": 0.34},
{"source": 460, "target": 712, "value": 0.06},
{"source": 465, "target": 930, "value": 0.05},
{"source": 465, "target": 698, "value": 0.05},
{"source": 465, "target": 523, "value": 0.53},
{"source": 468, "target": 577, "value": 0.17},
{"source": 475, "target": 895, "value": 0.05},
{"source": 475, "target": 898, "value": 0.06},
{"source": 475, "target": 603, "value": 0.06},
{"source": 475, "target": 814, "value": 0.07},
{"source": 476, "target": 645, "value": 0.17},
{"source": 482, "target": 595, "value": 0.07},
{"source": 483, "target": 577, "value": 0.08},
{"source": 495, "target": 565, "value": 0.08},
{"source": 496, "target": 714, "value": 0.21},
{"source": 502, "target": 627, "value": 0.15},
{"source": 503, "target": 952, "value": 0.53},
{"source": 504, "target": 880, "value": 0.03},
{"source": 504, "target": 638, "value": 0.09},
{"source": 505, "target": 743, "value": 0.09},
{"source": 522, "target": 873, "value": 0.27},
{"source": 528, "target": 959, "value": 0.03},
{"source": 528, "target": 787, "value": 0.03},
{"source": 528, "target": 801, "value": 0.05},
{"source": 531, "target": 611, "value": 0.26},
{"source": 533, "target": 964, "value": 0.15},
{"source": 543, "target": 885, "value": 0.26},
{"source": 555, "target": 694, "value": 0.17},
{"source": 564, "target": 768, "value": 0.08},
{"source": 565, "target": 589, "value": 0.10},
{"source": 565, "target": 659, "value": 0.10},
{"source": 566, "target": 653, "value": 0.04},
{"source": 567, "target": 712, "value": 0.05},
{"source": 570, "target": 910, "value": 0.06},
{"source": 572, "target": 598, "value": 0.06},
{"source": 573, "target": 868, "value": 0.05},
{"source": 574, "target": 648, "value": 0.10},
{"source": 576, "target": 628, "value": 0.06},
{"source": 577, "target": 696, "value": 0.05},
{"source": 577, "target": 763, "value": 0.05},
{"source": 577, "target": 750, "value": 0.06},
{"source": 578, "target": 841, "value": 0.07},
{"source": 579, "target": 666, "value": 0.06},
{"source": 580, "target": 948, "value": 0.20},
{"source": 581, "target": 895, "value": 0.03},
{"source": 581, "target": 758, "value": 0.04},
{"source": 582, "target": 607, "value": 0.10},
{"source": 582, "target": 835, "value": 0.53},
{"source": 583, "target": 648, "value": 0.03},
{"source": 583, "target": 617, "value": 0.04},
{"source": 585, "target": 607, "value": 0.04},
{"source": 586, "target": 620, "value": 0.04},
{"source": 586, "target": 870, "value": 0.06},
{"source": 587, "target": 871, "value": 0.06},
{"source": 588, "target": 648, "value": 0.04},
{"source": 590, "target": 873, "value": 0.03},
{"source": 591, "target": 704, "value": 0.07},
{"source": 592, "target": 735, "value": 0.04},
{"source": 593, "target": 815, "value": 0.06},
{"source": 596, "target": 669, "value": 0.04},
{"source": 601, "target": 895, "value": 0.06},
{"source": 602, "target": 936, "value": 0.05},
{"source": 602, "target": 677, "value": 0.05},
{"source": 602, "target": 789, "value": 0.05},
{"source": 602, "target": 615, "value": 0.07},
{"source": 604, "target": 740, "value": 0.05},
{"source": 605, "target": 895, "value": 0.06},
{"source": 606, "target": 960, "value": 0.05},
{"source": 607, "target": 684, "value": 0.04},
{"source": 607, "target": 769, "value": 0.05},
{"source": 607, "target": 722, "value": 0.21},
{"source": 609, "target": 667, "value": 0.04},
{"source": 610, "target": 896, "value": 0.05},
{"source": 611, "target": 842, "value": 0.08},
{"source": 611, "target": 668, "value": 0.08},
{"source": 613, "target": 712, "value": 0.04},
{"source": 614, "target": 762, "value": 0.06},
{"source": 615, "target": 728, "value": 0.34},
{"source": 616, "target": 740, "value": 0.06},
{"source": 618, "target": 648, "value": 0.05},
{"source": 619, "target": 657, "value": 0.03},
{"source": 619, "target": 886, "value": 0.08},
{"source": 620, "target": 869, "value": 0.07},
{"source": 621, "target": 712, "value": 0.03},
{"source": 621, "target": 804, "value": 0.07},
{"source": 622, "target": 873, "value": 0.05},
{"source": 624, "target": 653, "value": 0.05},
{"source": 625, "target": 648, "value": 0.03},
{"source": 626, "target": 789, "value": 0.34},
{"source": 628, "target": 970, "value": 0.04},
{"source": 628, "target": 752, "value": 0.05},
{"source": 629, "target": 631, "value": 0.18},
{"source": 631, "target": 632, "value": 0.06},
{"source": 633, "target": 895, "value": 0.03},
{"source": 633, "target": 720, "value": 0.06},
{"source": 635, "target": 882, "value": 0.34},
{"source": 637, "target": 960, "value": 0.05},
{"source": 639, "target": 910, "value": 0.03},
{"source": 641, "target": 653, "value": 0.08},
{"source": 642, "target": 959, "value": 0.05},
{"source": 643, "target": 704, "value": 0.04},
{"source": 643, "target": 658, "value": 0.05},
{"source": 643, "target": 697, "value": 0.11},
{"source": 645, "target": 953, "value": 0.07},
{"source": 646, "target": 864, "value": 0.22},
{"source": 647, "target": 652, "value": 0.04},
{"source": 648, "target": 660, "value": 0.03},
{"source": 648, "target": 783, "value": 0.03},
{"source": 648, "target": 895, "value": 0.03},
{"source": 648, "target": 700, "value": 0.03},
{"source": 648, "target": 695, "value": 0.03},
{"source": 648, "target": 924, "value": 0.04},
{"source": 648, "target": 881, "value": 0.04},
{"source": 648, "target": 780, "value": 0.04},
{"source": 648, "target": 665, "value": 0.04},
{"source": 648, "target": 756, "value": 0.05},
{"source": 648, "target": 747, "value": 0.06},
{"source": 648, "target": 766, "value": 0.08},
{"source": 648, "target": 670, "value": 0.14},
{"source": 649, "target": 961, "value": 0.04},
{"source": 649, "target": 889, "value": 0.06},
{"source": 650, "target": 700, "value": 0.04},
{"source": 651, "target": 712, "value": 0.04},
{"source": 652, "target": 921, "value": 0.03},
{"source": 652, "target": 799, "value": 0.04},
{"source": 652, "target": 882, "value": 0.05},
{"source": 652, "target": 656, "value": 0.06},
{"source": 652, "target": 904, "value": 0.08},
{"source": 653, "target": 690, "value": 0.04},
{"source": 653, "target": 793, "value": 0.15},
{"source": 655, "target": 712, "value": 0.05},
{"source": 657, "target": 778, "value": 0.03},
{"source": 657, "target": 712, "value": 0.03},
{"source": 662, "target": 890, "value": 0.06},
{"source": 662, "target": 913, "value": 0.06},
{"source": 663, "target": 827, "value": 0.05},
{"source": 667, "target": 712, "value": 0.03},
{"source": 667, "target": 689, "value": 0.04},
{"source": 667, "target": 680, "value": 0.05},
{"source": 669, "target": 713, "value": 0.05},
{"source": 669, "target": 941, "value": 0.06},
{"source": 671, "target": 966, "value": 0.04},
{"source": 672, "target": 954, "value": 0.08},
{"source": 673, "target": 811, "value": 0.10},
{"source": 674, "target": 767, "value": 0.06},
{"source": 675, "target": 896, "value": 0.04},
{"source": 676, "target": 791, "value": 0.08},
{"source": 677, "target": 933, "value": 0.04},
{"source": 678, "target": 910, "value": 0.04},
{"source": 681, "target": 712, "value": 0.05},
{"source": 682, "target": 778, "value": 0.03},
{"source": 683, "target": 762, "value": 0.10},
{"source": 686, "target": 873, "value": 0.05},
{"source": 688, "target": 895, "value": 0.11},
{"source": 691, "target": 961, "value": 0.05},
{"source": 691, "target": 899, "value": 0.06},
{"source": 693, "target": 910, "value": 0.04},
{"source": 693, "target": 902, "value": 0.05},
{"source": 694, "target": 824, "value": 0.04},
{"source": 694, "target": 866, "value": 0.05},
{"source": 695, "target": 704, "value": 0.03},
{"source": 695, "target": 708, "value": 0.06},
{"source": 695, "target": 863, "value": 0.10},
{"source": 699, "target": 924, "value": 0.06},
{"source": 702, "target": 789, "value": 0.05},
{"source": 703, "target": 855, "value": 0.05},
{"source": 703, "target": 878, "value": 0.06},
{"source": 704, "target": 888, "value": 0.06},
{"source": 705, "target": 962, "value": 0.04},
{"source": 709, "target": 891, "value": 0.04},
{"source": 712, "target": 723, "value": 0.03},
{"source": 712, "target": 735, "value": 0.03},
{"source": 712, "target": 948, "value": 0.03},
{"source": 712, "target": 762, "value": 0.03},
{"source": 712, "target": 830, "value": 0.03},
{"source": 712, "target": 933, "value": 0.03},
{"source": 712, "target": 927, "value": 0.03},
{"source": 712, "target": 760, "value": 0.04},
{"source": 712, "target": 743, "value": 0.04},
{"source": 712, "target": 716, "value": 0.04},
{"source": 712, "target": 961, "value": 0.04},
{"source": 712, "target": 721, "value": 0.05},
{"source": 712, "target": 939, "value": 0.05},
{"source": 712, "target": 779, "value": 0.05},
{"source": 712, "target": 771, "value": 0.05},
{"source": 712, "target": 845, "value": 0.05},
{"source": 712, "target": 918, "value": 0.06},
{"source": 712, "target": 802, "value": 0.06},
{"source": 712, "target": 749, "value": 0.06},
{"source": 712, "target": 745, "value": 0.07},
{"source": 712, "target": 947, "value": 0.08},
{"source": 712, "target": 931, "value": 0.15},
{"source": 714, "target": 834, "value": 0.13},
{"source": 720, "target": 816, "value": 0.06},
{"source": 724, "target": 780, "value": 0.07},
{"source": 725, "target": 729, "value": 0.03},
{"source": 729, "target": 773, "value": 0.04},
{"source": 729, "target": 823, "value": 0.07},
{"source": 731, "target": 857, "value": 0.11},
{"source": 732, "target": 966, "value": 0.03},
{"source": 733, "target": 961, "value": 0.07},
{"source": 734, "target": 966, "value": 0.04},
{"source": 735, "target": 739, "value": 0.04},
{"source": 735, "target": 908, "value": 0.04},
{"source": 738, "target": 953, "value": 0.07},
{"source": 744, "target": 896, "value": 0.04},
{"source": 746, "target": 809, "value": 0.17},
{"source": 752, "target": 951, "value": 0.08},
{"source": 753, "target": 960, "value": 0.09},
{"source": 761, "target": 916, "value": 0.06},
{"source": 761, "target": 850, "value": 0.07},
{"source": 762, "target": 843, "value": 0.04},
{"source": 767, "target": 813, "value": 0.05},
{"source": 767, "target": 893, "value": 0.11},
{"source": 772, "target": 927, "value": 0.17},
{"source": 774, "target": 868, "value": 0.05},
{"source": 781, "target": 800, "value": 0.07},
{"source": 785, "target": 855, "value": 0.08},
{"source": 786, "target": 944, "value": 0.04},
{"source": 788, "target": 797, "value": 0.06},
{"source": 791, "target": 836, "value": 0.08},
{"source": 792, "target": 806, "value": 0.04},
{"source": 805, "target": 916, "value": 0.04},
{"source": 805, "target": 833, "value": 0.05},
{"source": 806, "target": 895, "value": 0.04},
{"source": 807, "target": 815, "value": 0.06},
{"source": 809, "target": 936, "value": 0.05},
{"source": 810, "target": 952, "value": 0.03},
{"source": 812, "target": 884, "value": 0.05},
{"source": 815, "target": 950, "value": 0.04},
{"source": 822, "target": 906, "value": 0.06},
{"source": 826, "target": 958, "value": 0.09},
{"source": 827, "target": 859, "value": 0.04},
{"source": 828, "target": 966, "value": 0.06},
{"source": 830, "target": 852, "value": 0.05},
{"source": 830, "target": 937, "value": 0.10},
{"source": 832, "target": 895, "value": 0.05},
{"source": 838, "target": 902, "value": 0.06},
{"source": 843, "target": 853, "value": 0.09},
{"source": 847, "target": 852, "value": 0.17},
{"source": 855, "target": 894, "value": 0.05},
{"source": 872, "target": 952, "value": 0.04},
{"source": 876, "target": 892, "value": 0.10},
{"source": 881, "target": 922, "value": 0.06},
{"source": 884, "target": 896, "value": 0.04},
{"source": 885, "target": 895, "value": 0.04},
{"source": 886, "target": 919, "value": 0.34},
{"source": 891, "target": 912, "value": 0.53},
{"source": 892, "target": 967, "value": 0.04},
{"source": 895, "target": 914, "value": 0.05},
{"source": 895, "target": 969, "value": 0.05},
{"source": 896, "target": 962, "value": 0.03},
{"source": 900, "target": 909, "value": 0.04},
{"source": 903, "target": 966, "value": 0.06},
{"source": 925, "target": 927, "value": 0.04},
{"source": 926, "target": 938, "value": 0.11},
{"source": 960, "target": 966, "value": 0.03}
]
}
